<PAMDataset>
  <Metadata domain="Esri">
    <MDI key="PyramidResamplingType">NEAREST</MDI>
  </Metadata>
  <PAMRasterBand band="1">
    <Description>Layer_1</Description>
    <Metadata>
      <MDI key="LAYER_TYPE">athematic</MDI>
      <MDI key="STATISTICS_EXCLUDEDVALUES">0</MDI>
      <MDI key="STATISTICS_HISTOBINVALUES">0|0|0|0|0|0|0|0|0|0|0|16|5776|912|64868|167672|10056|205552|187560|12072|230168|235316|207952|17016|239808|194944|16540|202220|170676|15280|153140|133600|14008|129580|107812|13060|116016|107224|12600|100136|104164|93188|11292|91284|80144|10948|77044|84912|76564|9648|78028|73020|10060|68616|70848|66144|9256|62612|64680|63192|9524|58212|110872|8300|6532|54536|52828|50192|51996|7648|50608|51780|49360|46120|6980|46592|44900|42096|43084|6412|43492|40372|42708|40056|39564|6040|37068|37240|39368|36012|37448|36872|5584|33912|34376|34460|32260|32868|33508|5208|31240|32220|31644|30888|29392|29092|30304|28968|29384|4740|29252|27544|28128|29068|48756|5268|50060|25884|4108|25256|24792|3820|23864|23880|25052|23408|23756|23832|22852|22384|22764|21048|3596|21972|22352|21764|21596|21604|21632|19996|20856|21128|20468|20360|21076|19456|20092|19728|19016|19616|19948|18576|19600|19756|19272|17580|33752|18296|18228|18564|17408|18424|31984|18260|18048|30804|18472|16636|29440|17160|16312|17064|29852|16700|41056|4084|16184|27236|15436|38376|3908|26168|26952|14284|14224|25816|25084|13508|24444|13276|22488|13248|23108|21856|12116|20448|20216|11588|11260|19408|10240|19680|18056|10292|9456|17100|9460|17340|9620|17172|15868|1616|15460|8188|7972|14784|7600|7360|7120|18728|1264|6304|6132|6216|10688|5076|5432|5284|5120|4556|4372|4044|3832|7472|3412|3144|2872|2588|2288|1888|1980|1836|1820|1724|1556|1316|1132|820|792|696|520|296|256|200|164|60|</MDI>
      <MDI key="STATISTICS_HISTOMAX">255</MDI>
      <MDI key="STATISTICS_HISTOMIN">0</MDI>
      <MDI key="STATISTICS_HISTONUMBINS">256</MDI>
      <MDI key="STATISTICS_MAXIMUM">255</MDI>
      <MDI key="STATISTICS_MEAN">77.813138020739</MDI>
      <MDI key="STATISTICS_MEDIAN">57</MDI>
      <MDI key="STATISTICS_MINIMUM">11</MDI>
      <MDI key="STATISTICS_MODE">24</MDI>
      <MDI key="STATISTICS_SKIPFACTORX">2</MDI>
      <MDI key="STATISTICS_SKIPFACTORY">2</MDI>
      <MDI key="STATISTICS_STDDEV">58.905223811734</MDI>
    </Metadata>
  </PAMRasterBand>
</PAMDataset>
